sqlite_middleware/__init__.py
sqlite_middleware/database.py
sqlite_middleware-0.0.3.dist-info/LICENSE
sqlite_middleware-0.0.3.dist-info/METADATA
sqlite_middleware-0.0.3.dist-info/WHEEL
sqlite_middleware-0.0.3.dist-info/top_level.txt
sqlite_middleware-0.0.3.dist-info/RECORD
