Metadata-Version: 2.1
Name: sqlite-middleware
Version: 0.0.3
Summary: This is a python package that makes it easier to work with sqlite
Home-page: https://github.com/JefvdA/sqlite_middleware
Author: JefvdA
Author-email: jef.v.d.a@live.be
Project-URL: Bug Tracker, https://github.com/JefvdA/sqlite_middleware/issues
Classifier: Programming Language :: Python :: 3
Classifier: License :: OSI Approved :: MIT License
Classifier: Operating System :: OS Independent
Requires-Python: >=3.6
License-File: LICENSE
